spatter/__init__.py
spatter/__main__.py
spatter/py.typed
spatter-0.0.0.dist-info/entry_points.txt
spatter-0.0.0.dist-info/LICENSE.rst
spatter-0.0.0.dist-info/WHEEL
spatter-0.0.0.dist-info/METADATA
spatter-0.0.0.dist-info/RECORD
