Metadata-Version: 2.1
Name: spatter
Version: 0.0.0
Summary: Spatter
Home-page: https://github.com/jriddy/spatter
License: MIT
Author: Josh Reed
Author-email: jriddy@gmail.com
Requires-Python: >=3.6.1,<4.0.0
Classifier: License :: OSI Approved :: MIT License
Classifier: Programming Language :: Python :: 3
Classifier: Programming Language :: Python :: 3.6
Classifier: Programming Language :: Python :: 3.7
Classifier: Programming Language :: Python :: 3.8
Classifier: Programming Language :: Python :: 3.9
Requires-Dist: click (>=7.0,<8.0)
Project-URL: Changelog, https://github.com/jriddy/spatter/releases
Project-URL: Documentation, https://spatter.readthedocs.io
Project-URL: Repository, https://github.com/jriddy/spatter
